je_editor/__init__.py
je_editor/__main__.py
je_editor/start_editor.py
je_editor/code_scan/__init__.py
je_editor/code_scan/ruff_thread.py
je_editor/code_scan/watchdog_implement.py
je_editor/code_scan/watchdog_thread.py
je_editor/git_client/__init__.py
je_editor/git_client/commit_graph.py
je_editor/git_client/git_action.py
je_editor/git_client/git_cli.py
je_editor/pyside_ui/__init__.py
je_editor/pyside_ui/browser/__init__.py
je_editor/pyside_ui/browser/browser_download_window.py
je_editor/pyside_ui/browser/browser_serach_lineedit.py
je_editor/pyside_ui/browser/browser_view.py
je_editor/pyside_ui/browser/browser_widget.py
je_editor/pyside_ui/browser/main_browser_widget.py
je_editor/pyside_ui/code/__init__.py
je_editor/pyside_ui/code/running_process_manager.py
je_editor/pyside_ui/code/auto_save/__init__.py
je_editor/pyside_ui/code/auto_save/auto_save_manager.py
je_editor/pyside_ui/code/auto_save/auto_save_thread.py
je_editor/pyside_ui/code/code_format/__init__.py
je_editor/pyside_ui/code/code_format/pep8_format.py
je_editor/pyside_ui/code/code_process/__init__.py
je_editor/pyside_ui/code/code_process/code_exec.py
je_editor/pyside_ui/code/plaintext_code_edit/__init__.py
je_editor/pyside_ui/code/plaintext_code_edit/code_edit_plaintext.py
je_editor/pyside_ui/code/shell_process/__init__.py
je_editor/pyside_ui/code/shell_process/shell_exec.py
je_editor/pyside_ui/code/syntax/__init__.py
je_editor/pyside_ui/code/syntax/python_syntax.py
je_editor/pyside_ui/code/syntax/syntax_setting.py
je_editor/pyside_ui/code/textedit_code_result/__init__.py
je_editor/pyside_ui/code/textedit_code_result/code_record.py
je_editor/pyside_ui/code/variable_inspector/__init__.py
je_editor/pyside_ui/code/variable_inspector/inspector_gui.py
je_editor/pyside_ui/dialog/__init__.py
je_editor/pyside_ui/dialog/ai_dialog/__init__.py
je_editor/pyside_ui/dialog/ai_dialog/set_ai_dialog.py
je_editor/pyside_ui/dialog/file_dialog/__init__.py
je_editor/pyside_ui/dialog/file_dialog/create_file_dialog.py
je_editor-0.0.235.dist-info/licenses/LICENSE
je_editor-0.0.235.dist-info/METADATA
je_editor-0.0.235.dist-info/WHEEL
je_editor-0.0.235.dist-info/top_level.txt
je_editor-0.0.235.dist-info/RECORD
