Metadata-Version: 2.4
Name: je_editor
Version: 0.0.235
Summary: JEditor is basic but powerful editor include GPT
Author-email: JE-Chen <jechenmailman@gmail.com>
Project-URL: Homepage, https://github.com/JE-Chen/je_editor
Project-URL: Documentation, https://je-editor.readthedocs.io/en/latest/
Project-URL: Code, https://github.com/JE-Chen/je_editor
Classifier: Programming Language :: Python :: 3.10
Classifier: Development Status :: 2 - Pre-Alpha
Classifier: Environment :: Win32 (MS Windows)
Classifier: Environment :: MacOS X
Classifier: Environment :: X11 Applications
Classifier: License :: OSI Approved :: MIT License
Classifier: Operating System :: OS Independent
Requires-Python: >=3.10
License-File: LICENSE
Requires-Dist: PySide6==6.10.1
Requires-Dist: qt-material
Requires-Dist: yapf
Requires-Dist: frontengine
Requires-Dist: pycodestyle
Requires-Dist: jedi
Requires-Dist: qtconsole
Requires-Dist: langchain_openai==1.1.0
Requires-Dist: langchain==1.1.2
Requires-Dist: pydantic
Requires-Dist: watchdog
Requires-Dist: ruff
Requires-Dist: gitpython
Dynamic: license-file
